wize.py
wxWize-1.2.0.dist-info/METADATA
wxWize-1.2.0.dist-info/WHEEL
wxWize-1.2.0.dist-info/top_level.txt
wxWize-1.2.0.dist-info/RECORD
