Metadata-Version: 2.1
Name: wxWize
Version: 1.2.0
Summary: wxPython object builder
Home-page: https://github.com/AndersMunch/wxWize
Author: Anders Munch
Author-email: anders@jmunch.dk
License: WTFPL
Keywords: wxPython wxWidgets sizers
Platform: UNKNOWN
Classifier: Development Status :: 5 - Production/Stable
Classifier: Programming Language :: Python :: 2
Classifier: Programming Language :: Python :: 3
Classifier: Intended Audience :: Developers
Classifier: Environment :: MacOS X :: Carbon
Classifier: Environment :: Win32 (MS Windows)
Classifier: Environment :: X11 Applications :: GTK
Classifier: Operating System :: MacOS :: MacOS X
Classifier: Operating System :: Microsoft :: Windows
Classifier: Operating System :: POSIX
Classifier: Topic :: Software Development :: User Interfaces 
